tuning_fork/__init__.py
tuning_fork/main.py
tuning_fork/tools/__init__.py
tuning_fork/tools/analysis.py
tuning_fork/tools/parseMusic.py
tuning_fork-1.7.1.dist-info/METADATA
tuning_fork-1.7.1.dist-info/RECORD
tuning_fork-1.7.1.dist-info/WHEEL
tuning_fork-1.7.1.dist-info/top_level.txt
