Metadata-Version: 2.1
Name: tuning-fork
Version: 1.7.1
Summary: A clip/sample auto tuner
Home-page: https://github.com/ddxtanx/TuningFork
Author: Garrett Credi
Author-email: gcc@ameritech.net
License: UNKNOWN
Platform: UNKNOWN
Classifier: Development Status :: 5 - Production/Stable
Classifier: Environment :: Console
Classifier: Intended Audience :: Developers
Classifier: Natural Language :: English
Classifier: Programming Language :: Python :: 3.6
Classifier: License :: OSI Approved :: MIT License
Classifier: Operating System :: OS Independent
Classifier: Topic :: Multimedia :: Sound/Audio :: Mixers
Classifier: Topic :: Multimedia :: Sound/Audio :: Analysis
Classifier: Topic :: Utilities
Requires-Dist: librosa
Requires-Dist: numpy
Requires-Dist: pysoundfile
